HISTORY.rst
LICENCE.txt
MANIFEST.in
README.rst
setup.py
pypepa/__init__.py
pypepa/exceptions.py
pypepa/logger.py
pypepa/pepa_model.py
pypepa/utils.py
pypepa.egg-info/PKG-INFO
pypepa.egg-info/SOURCES.txt
pypepa.egg-info/dependency_links.txt
pypepa.egg-info/entry_points.txt
pypepa.egg-info/not-zip-safe
pypepa.egg-info/requires.txt
pypepa.egg-info/top_level.txt
pypepa/cli/__init__.py
pypepa/cli/cli.py
pypepa/derivation/__init__.py
pypepa/derivation/old_ss.py
pypepa/derivation/state_space.py
pypepa/experiments/__init__.py
pypepa/experiments/experiment.py
pypepa/experiments/graphing.py
pypepa/parsing/__init__.py
pypepa/parsing/comp_state_space_graph.py
pypepa/parsing/component_state_visitor.py
pypepa/parsing/fourFn.py
pypepa/parsing/parser.py
pypepa/parsing/pepa_ast.py
pypepa/parsing/pepa_treewalker.py
pypepa/parsing/rate_parser.py
pypepa/solvers/__init__.py
pypepa/solvers/ctmc.py
pypepa/solvers/solution.py