Metadata-Version: 1.1
Name: pypepa
Version: 0.4.12
Summary: pypepa is a PEPA library and a toolset for PEPA.
Home-page: https://github.com/tdi/pyPEPA
Author: Dariusz Dwornikowski
Author-email: dariusz.dwornikowski@cs.put.poznan.pl
License: Apache Common 2.0
Platform: UNKNOWN
Classifier: Environment :: Console
Classifier: Development Status :: 4 - Beta
Classifier: Programming Language :: Python
Classifier: Programming Language :: Python :: 3.3
Classifier: License :: OSI Approved :: Apache Software License
Classifier: Intended Audience :: Science/Research
Classifier: Operating System :: POSIX
Requires: numpy (>=1.6.7)
Requires: scipy (>=0.10)
Requires: pyparsing (>=2.0.0)
Requires: matplotlib (>=1.2.0)
